opengeode_geode/__init__.py
opengeode_geode/model.py
opengeode_geode/bin/OpenGeode_geode_model.dll
opengeode_geode/bin/opengeode_geode_py_model.cp38-win_amd64.pyd
OpenGeode_core.geode-1.7.27.dist-info/METADATA
OpenGeode_core.geode-1.7.27.dist-info/WHEEL
OpenGeode_core.geode-1.7.27.dist-info/top_level.txt
OpenGeode_core.geode-1.7.27.dist-info/RECORD
