Metadata-Version: 2.1
Name: OpenGeode-core.geode
Version: 1.7.27
Summary: Geode extension for OpenGeode
Home-page: https://github.com/Geode-solutions/OpenGeode_geode
Author: Geode-solutions
Author-email: contact@geode-solutions.com
License: MIT
Platform: UNKNOWN
Requires-Dist: opengeode-core ==14.*,>=14.9.3
